MANIFEST.in
README.rst
setup.py
Rels.egg-info/PKG-INFO
Rels.egg-info/SOURCES.txt
Rels.egg-info/dependency_links.txt
Rels.egg-info/top_level.txt
helpers/example.py
rels/__init__.py
rels/django.py
rels/exceptions.py
rels/relations.py
rels/shortcuts.py
rels/tests.py