Metadata-Version: 1.1
Name: Rels
Version: 0.3.0
Summary: Library for describing data relations in python (Enums, "relational" tables)
Home-page: https://github.com/Tiendil/rels
Author: Aleksey Yeletsky <Tiendil>
Author-email: a.eletsky@gmail.com
License: BSD
Keywords: enums,data relations,relational tables
Platform: UNKNOWN
Classifier: Development Status :: 5 - Production/Stable
Classifier: Intended Audience :: Developers
Classifier: Topic :: Software Development :: Libraries :: Python Modules
Classifier: License :: OSI Approved :: BSD License
Classifier: Programming Language :: Python :: 3
Classifier: Programming Language :: Python :: 3.5
Classifier: Natural Language :: English
Classifier: Natural Language :: Russian
